dxlepoclient/__init__.py
dxlepoclient/_version.py
dxlepoclient/client.py
dxlepoclient/_config/__init__.py
dxlepoclient/_config/sample/__init__.py
dxlepoclient/_config/sample/dxlclient.config
dxlepoclient-0.2.2.dist-info/METADATA
dxlepoclient-0.2.2.dist-info/RECORD
dxlepoclient-0.2.2.dist-info/WHEEL
dxlepoclient-0.2.2.dist-info/top_level.txt
